LICENSE.txt
MANIFEST.in
README.md
requirements.txt
setup.py
txKeystone/__init__.py
txKeystone/keystone.py
txKeystone.egg-info/PKG-INFO
txKeystone.egg-info/SOURCES.txt
txKeystone.egg-info/dependency_links.txt
txKeystone.egg-info/requires.txt
txKeystone.egg-info/top_level.txt
txKeystone/test/__init__.py
txKeystone/test/test_agent.py
utils/__init__.py
utils/dist.py