Metadata-Version: 1.0
Name: txKeystone
Version: 0.1.3
Summary: A Twisted Agent implementation which authenticates to Keystone and uses the Keystone auth credentials to authenticate against requested urls.
Home-page: https://github.com/racker/python-twisted-keystone-agent
Author: Rackspace Hosting, Inc.
Author-email: sr@rackspace.com
License: Apache License (2.0)
Platform: UNKNOWN
Classifier: Development Status :: 4 - Beta
Classifier: License :: OSI Approved :: Apache Software License
Classifier: Programming Language :: Python :: 2.5
Classifier: Programming Language :: Python :: 2.6
Classifier: Programming Language :: Python :: 2.7
Classifier: Programming Language :: Python :: Implementation :: PyPy
Classifier: Framework :: Twisted
